albibong/__init__.py
albibong/__main__.py
albibong/requirements.txt
albibong/assets/boom_small.mp3
albibong/classes/__init__.py
albibong/classes/character.py
albibong/classes/coords.py
albibong/classes/dungeon.py
albibong/classes/item.py
albibong/classes/location.py
albibong/classes/logger.py
albibong/classes/packet_handler.py
albibong/classes/utils.py
albibong/classes/world_data.py
albibong/classes/event_handler/__init__.py
albibong/classes/event_handler/handle_event_character_equipment_changed.py
albibong/classes/event_handler/handle_event_health.py
albibong/classes/event_handler/handle_event_in_combat_state_update.py
albibong/classes/event_handler/handle_event_might_and_favor_received_event.py
albibong/classes/event_handler/handle_event_new_character.py
albibong/classes/event_handler/handle_event_other_grabbed_loot.py
albibong/classes/event_handler/handle_event_party.py
albibong/classes/event_handler/handle_event_update_fame.py
albibong/classes/event_handler/handle_event_update_re_spec_points.py
albibong/classes/event_handler/handle_operation_change_cluster.py
albibong/classes/event_handler/handle_operation_farmable_harvest.py
albibong/classes/event_handler/handle_operation_join.py
albibong/classes/event_handler/handle_operation_move.py
albibong/classes/event_handler/world_data_utils.py
albibong/gui_dist/Albibong.png
albibong/gui_dist/No Equipment.png
albibong/gui_dist/fame.png
albibong/gui_dist/favor.png
albibong/gui_dist/index.html
albibong/gui_dist/might.png
albibong/gui_dist/re_spec.png
albibong/gui_dist/silver.png
albibong/gui_dist/vite.svg
albibong/gui_dist/assets/index-B31tZ4Ku.css
albibong/gui_dist/assets/index-BkyL_QUY.js
albibong/migrations/001_init.py
albibong/migrations/002_alter_dungeon_table.py
albibong/models/__init__.py
albibong/models/models.py
albibong/photon_packet_parser/__init__.py
albibong/photon_packet_parser/command_type.py
albibong/photon_packet_parser/crc_calculator.py
albibong/photon_packet_parser/event_data.py
albibong-1.1.8.dist-info/METADATA
albibong-1.1.8.dist-info/WHEEL
albibong-1.1.8.dist-info/entry_points.txt
albibong-1.1.8.dist-info/licenses/LICENSE
albibong-1.1.8.dist-info/RECORD
