Metadata-Version: 2.4
Name: albibong
Version: 1.1.8
Summary: A cross-platform Albion Online damage, fame, and dungeon tracker
Project-URL: Homepage, https://github.com/imjangkar/albibong
Project-URL: Issues, https://github.com/imjangkar/albibong/issues
Author-email: imjangkar <imjangkar@gmail.com>
License-File: LICENSE
Classifier: License :: OSI Approved :: MIT License
Classifier: Operating System :: OS Independent
Classifier: Programming Language :: Python :: 3
Requires-Python: >=3.10
Requires-Dist: peewee-migrate==1.13.0
Requires-Dist: peewee==3.17.6
Requires-Dist: pywebview==5.1
Requires-Dist: scapy==2.5.0
Requires-Dist: websockets==12.0
